[
	{
		"selected": false,
		"imgUrl": "001-x.png",
		"xy": "x"
	},
	{
		"selected": false,
		"imgUrl": "013-y.png",
		"xy": "y"
	},
	{
		"selected": false,
		"imgUrl": "025-y.png",
		"xy": "y"
	},
	{
		"selected": false,
		"imgUrl": "037-x.png",
		"xy": "x"
	},
	{
		"selected": false,
		"imgUrl": "049-y.png",
		"xy": "y"
	},
	{
		"selected": false,
		"imgUrl": "071-y.png",
		"xy": "y"
	},
	{
		"selected": false,
		"imgUrl": "084-x.png",
		"xy": "x"
	},
	{
		"selected": false,
		"imgUrl": "096-y.png",
		"xy": "y"
	},
	{
		"selected": false,
		"imgUrl": "002-y.png",
		"xy": "y"
	},
	{
		"selected": false,
		"imgUrl": "014-y.png",
		"xy": "y"
	},
	{
		"selected": false,
		"imgUrl": "026-x.png",
		"xy": "x"
	},
	{
		"selected": false,
		"imgUrl": "038-x.png",
		"xy": "x"
	},
	{
		"selected": false,
		"imgUrl": "050-y.png",
		"xy": "y"
	},
	{
		"selected": false,
		"imgUrl": "072-x.png",
		"xy": "x"
	},
	{
		"selected": false,
		"imgUrl": "085-x.png",
		"xy": "x"
	},
	{
		"selected": false,
		"imgUrl": "097-x.png",
		"xy": "x"
	},
	{
		"selected": false,
		"imgUrl": "003-y.png",
		"xy": "y"
	},
	{
		"selected": false,
		"imgUrl": "015-x.png",
		"xy": "x"
	},
	{
		"selected": false,
		"imgUrl": "027-y.png",
		"xy": "y"
	},
	{
		"selected": false,
		"imgUrl": "039-y.png",
		"xy": "y"
	},
	{
		"selected": false,
		"imgUrl": "061-x.png",
		"xy": "x"
	},
	{
		"selected": false,
		"imgUrl": "073-x.png",
		"xy": "x"
	},
	{
		"selected": false,
		"imgUrl": "086-x.png",
		"xy": "x"
	},
	{
		"selected": false,
		"imgUrl": "098-x.png",
		"xy": "x"
	},
	{
		"selected": false,
		"imgUrl": "004-y.png",
		"xy": "y"
	},
	{
		"selected": false,
		"imgUrl": "016-y.png",
		"xy": "y"
	},
	{
		"selected": false,
		"imgUrl": "028-y.png",
		"xy": "y"
	},
	{
		"selected": false,
		"imgUrl": "040-x.png",
		"xy": "x"
	},
	{
		"selected": false,
		"imgUrl": "062-y.png",
		"xy": "y"
	},
	{
		"selected": false,
		"imgUrl": "074-y.png",
		"xy": "y"
	},
	{
		"selected": false,
		"imgUrl": "087-x.png",
		"xy": "x"
	},
	{
		"selected": false,
		"imgUrl": "099-y.png",
		"xy": "y"
	},
	{
		"selected": false,
		"imgUrl": "005-y.png",
		"xy": "y"
	},
	{
		"selected": false,
		"imgUrl": "017-y.png",
		"xy": "y"
	},
	{
		"selected": false,
		"imgUrl": "029-y.png",
		"xy": "y"
	},
	{
		"selected": false,
		"imgUrl": "041-y.png",
		"xy": "y"
	},
	{
		"selected": false,
		"imgUrl": "063-y.png",
		"xy": "y"
	},
	{
		"selected": false,
		"imgUrl": "075-x.png",
		"xy": "x"
	},
	{
		"selected": false,
		"imgUrl": "088-x.png",
		"xy": "x"
	},
	{
		"selected": false,
		"imgUrl": "100-x.png",
		"xy": "x"
	},
	{
		"selected": false,
		"imgUrl": "006-y.png",
		"xy": "y"
	},
	{
		"selected": false,
		"imgUrl": "018-x.png",
		"xy": "x"
	},
	{
		"selected": false,
		"imgUrl": "030-x.png",
		"xy": "x"
	},
	{
		"selected": false,
		"imgUrl": "042-x.png",
		"xy": "x"
	},
	{
		"selected": false,
		"imgUrl": "064-y.png",
		"xy": "y"
	},
	{
		"selected": false,
		"imgUrl": "076-x.png",
		"xy": "x"
	},
	{
		"selected": false,
		"imgUrl": "089-x.png",
		"xy": "x"
	},
	{
		"selected": false,
		"imgUrl": "101-x.png",
		"xy": "x"
	},
	{
		"selected": false,
		"imgUrl": "007-x.png",
		"xy": "x"
	},
	{
		"selected": false,
		"imgUrl": "019-x.png",
		"xy": "x"
	},
	{
		"selected": false,
		"imgUrl": "031-y.png",
		"xy": "y"
	},
	{
		"selected": false,
		"imgUrl": "043-x.png",
		"xy": "x"
	},
	{
		"selected": false,
		"imgUrl": "065-y.png",
		"xy": "y"
	},
	{
		"selected": false,
		"imgUrl": "077-y.png",
		"xy": "y"
	},
	{
		"selected": false,
		"imgUrl": "090-x.png",
		"xy": "x"
	},
	{
		"selected": false,
		"imgUrl": "102-y.png",
		"xy": "y"
	},
	{
		"selected": false,
		"imgUrl": "008-x.png",
		"xy": "x"
	},
	{
		"selected": false,
		"imgUrl": "020-x.png",
		"xy": "x"
	},
	{
		"selected": false,
		"imgUrl": "032-x.png",
		"xy": "x"
	},
	{
		"selected": false,
		"imgUrl": "044-y.png",
		"xy": "y"
	},
	{
		"selected": false,
		"imgUrl": "066-y.png",
		"xy": "y"
	},
	{
		"selected": false,
		"imgUrl": "079-x.png",
		"xy": "x"
	},
	{
		"selected": false,
		"imgUrl": "091-x.png",
		"xy": "x"
	},
	{
		"selected": false,
		"imgUrl": "103-x.png",
		"xy": "x"
	},
	{
		"selected": false,
		"imgUrl": "009-x.png",
		"xy": "x"
	},
	{
		"selected": false,
		"imgUrl": "021-y.png",
		"xy": "y"
	},
	{
		"selected": false,
		"imgUrl": "033-x.png",
		"xy": "x"
	},
	{
		"selected": false,
		"imgUrl": "045-y.png",
		"xy": "y"
	},
	{
		"selected": false,
		"imgUrl": "067-y.png",
		"xy": "y"
	},
	{
		"selected": false,
		"imgUrl": "080-y.png",
		"xy": "y"
	},
	{
		"selected": false,
		"imgUrl": "092-x.png",
		"xy": "x"
	},
	{
		"selected": false,
		"imgUrl": "104-x.png",
		"xy": "x"
	},
	{
		"selected": false,
		"imgUrl": "010-x.png",
		"xy": "x"
	},
	{
		"selected": false,
		"imgUrl": "022-x.png",
		"xy": "x"
	},
	{
		"selected": false,
		"imgUrl": "034-x.png",
		"xy": "x"
	},
	{
		"selected": false,
		"imgUrl": "046-x.png",
		"xy": "x"
	},
	{
		"selected": false,
		"imgUrl": "068-x.png",
		"xy": "x"
	},
	{
		"selected": false,
		"imgUrl": "081-y.png",
		"xy": "y"
	},
	{
		"selected": false,
		"imgUrl": "093-x.png",
		"xy": "x"
	},
	{
		"selected": false,
		"imgUrl": "011-y.png",
		"xy": "y"
	},
	{
		"selected": false,
		"imgUrl": "023-y.png",
		"xy": "y"
	},
	{
		"selected": false,
		"imgUrl": "035-y.png",
		"xy": "y"
	},
	{
		"selected": false,
		"imgUrl": "047-y.png",
		"xy": "y"
	},
	{
		"selected": false,
		"imgUrl": "069-y.png",
		"xy": "y"
	},
	{
		"selected": false,
		"imgUrl": "082-x.png",
		"xy": "x"
	},
	{
		"selected": false,
		"imgUrl": "094-x.png",
		"xy": "x"
	},
	{
		"selected": false,
		"imgUrl": "012-y.png",
		"xy": "y"
	},
	{
		"selected": false,
		"imgUrl": "024-x.png",
		"xy": "x"
	},
	{
		"selected": false,
		"imgUrl": "036-y.png",
		"xy": "y"
	},
	{
		"selected": false,
		"imgUrl": "048-y.png",
		"xy": "y"
	},
	{
		"selected": false,
		"imgUrl": "070-x.png",
		"xy": "x"
	},
	{
		"selected": false,
		"imgUrl": "083-x.png",
		"xy": "x"
	},
	{
		"selected": false,
		"imgUrl": "095-x.png",
		"xy": "x"
	}
]
